blackspammerbd/__init__.py
blackspammerbd/core.py
blackspammerbd1/__init__.py
blackspammerbd1/server.py
blackspammerbd_bsb/__init__.py
blackspammerbd_bsb/cli.py
blackspammerbd_one/__init__.py
blackspammerbd_one/cli.py
blackspammerbd_v1/__init__.py
blackspammerbd_v1/cli.py
blackspammerbd_v1-1.0.1.dist-info/LICENSE.chromedriver
blackspammerbd_v1-1.0.1.dist-info/METADATA
blackspammerbd_v1-1.0.1.dist-info/WHEEL
blackspammerbd_v1-1.0.1.dist-info/entry_points.txt
blackspammerbd_v1-1.0.1.dist-info/top_level.txt
blackspammerbd_v1-1.0.1.dist-info/RECORD
